Metadata-Version: 1.0
Name: wwx
Version: 0.2.11
Summary: a library for wx Developer
Home-page: https://github.com/wxnacy/wwx
Author: wxnacy
Author-email: wxnacy@gmail.com
License: MIT License
Keywords: wx
Platform: any
